setup.py
elasticsearch_parse/__init__.py
elasticsearch_parse/aggs.py
elasticsearch_parse/exceptions.py
elasticsearch_parse/faceted_search.py
elasticsearch_parse/filter.py
elasticsearch_parse/index.py
elasticsearch_parse/query.py
elasticsearch_parse/search.py
elasticsearch_parse/serializer.py
elasticsearch_parse/utils.py
elasticsearch_parse.egg-info/PKG-INFO
elasticsearch_parse.egg-info/SOURCES.txt
elasticsearch_parse.egg-info/dependency_links.txt
elasticsearch_parse.egg-info/requires.txt
elasticsearch_parse.egg-info/top_level.txt