Metadata-Version: 1.1
Name: elasticsearch-parse
Version: 2.0
Summary: elasticsearch parse
Home-page: http://xiaorui.cc
Author: ruifengyun
Author-email: rfyiamcool@163.com
License: MIT
Keywords: elasticsearch_parse,fengyun
Platform: UNKNOWN
Classifier: Development Status :: 2 - Pre-Alpha
Classifier: Intended Audience :: Developers
Classifier: License :: OSI Approved :: MIT License
Classifier: Programming Language :: Python :: 2.6
Classifier: Programming Language :: Python :: 2.7
Classifier: Programming Language :: Python :: 3.0
Classifier: Topic :: Software Development :: Libraries :: Python Modules
